json_include/__init__.py
json_include/__main__.py
json_include/json_include.py
krozark_json_include-3.3.2.dist-info/LICENSE
krozark_json_include-3.3.2.dist-info/METADATA
krozark_json_include-3.3.2.dist-info/WHEEL
krozark_json_include-3.3.2.dist-info/entry_points.txt
krozark_json_include-3.3.2.dist-info/top_level.txt
krozark_json_include-3.3.2.dist-info/RECORD
