Metadata-Version: 2.1
Name: krozark-json-include
Version: 3.3.2
Summary: An extension for json_include to support file inclusion
Home-page: https://github.com/Krozark/json_include
Author: Maxime Barbier
Author-email: maxime.barbier1991+json-include@gmail.com
License: MIT License
Keywords: json include
Classifier: Programming Language :: Python
Classifier: Programming Language :: Python :: 3
Classifier: Intended Audience :: Developers
Classifier: Topic :: Software Development
Classifier: Operating System :: OS Independent
Requires-Python: >=3.6
License-File: LICENSE
